eodo/__init__.py
eodo/app.py
eodo/static/index.html
eodo-0.1.17.dist-info/METADATA
eodo-0.1.17.dist-info/WHEEL
eodo-0.1.17.dist-info/entry_points.txt
eodo-0.1.17.dist-info/RECORD
