Metadata-Version: 2.4
Name: eodo
Version: 0.1.17
Summary: EdgeOneDynamicOrigin
Requires-Python: >=3.12
Requires-Dist: fastapi
Requires-Dist: psutil
Requires-Dist: pyyaml
Requires-Dist: requests
Requires-Dist: schedule
Requires-Dist: uvicorn
